cortile/__init__.py
cortile/cortile.py
cortile/base/__init__.py
cortile/base/connector.py
cortile/base/process.py
cortile/base/session.py
cortile/helper/__init__.py
cortile/helper/dict.py
cortile/helper/logger.py
cortile/helper/signal.py
cortile/helper/time.py
cortile-1.0.0.dist-info/METADATA
cortile-1.0.0.dist-info/WHEEL
cortile-1.0.0.dist-info/licenses/LICENSE
cortile-1.0.0.dist-info/RECORD
