Metadata-Version: 2.3
Name: cortile
Version: 1.0.0
Summary: Python bindings for the linux auto tiling manager cortile.
Project-URL: Homepage, https://github.com/leukipp/cortile
Project-URL: Repository, https://github.com/leukipp/cortile-addons
Author: leukipp
License: MIT License
License-File: LICENSE
Keywords: dbus,x11
Classifier: Intended Audience :: Developers
Classifier: License :: OSI Approved :: MIT License
Classifier: Programming Language :: Python
Classifier: Programming Language :: Python :: 3
Classifier: Programming Language :: Python :: 3.8
Classifier: Programming Language :: Python :: 3.9
Classifier: Programming Language :: Python :: 3.10
Classifier: Programming Language :: Python :: 3.11
Classifier: Programming Language :: Python :: 3.12
Requires-Python: >=3.8
Requires-Dist: dbus-python>=1.3.2
Provides-Extra: dev
Requires-Dist: hatch>=1.12.0; extra == 'dev'
